#### 问题收集

1.你知道基本数据类型占用的字节数么？boolean呢？

2.short s=1; s+=1; 编译会有异常么？为什么？

3.你如何确定是否发生类型转换呢？

好，看完这边文章，你心中的疑惑将被一一解答。

#### 基本类型

java提供了8种数据类型，分别用来表示：整型，浮点型，字符型，布尔型；

整型：byte，short，int，long

浮点型：float，double

字符型：char

布尔型：boolean

##### byte

    基本类型：byte 二进制位数：8
    占字节数：1字节
    包装类：java.lang.Byte
    最小值：Byte.MIN_VALUE=-128
    最大值：Byte.MAX_VALUE=127
    默认值：1

##### short

    基本类型：short 二进制位数：16
    占字节数：2字节
    包装类：java.lang.Short
    最小值：Short.MIN_VALUE=-32768
    最大值：Short.MAX_VALUE=32767
    默认值：1

##### int

    基本类型：int 二进制位数：32
    占字节数：4字节
    包装类：java.lang.Integer
    最小值：Integer.MIN_VALUE=-2147483648
    最大值：Integer.MAX_VALUE=2147483647
    默认值：1

##### long

    基本类型：long 二进制位数：64
    占字节数：8字节
    包装类：java.lang.Long
    最小值：Long.MIN_VALUE=-9223372036854775808
    最大值：Long.MAX_VALUE=9223372036854775807
    默认值：1L

##### float

    基本类型：float 二进制位数：32
    位数组成：符号位=1，指数位=8(其中指数符号位=1)，尾数位=23
    占字节数：4字节
    包装类：java.lang.Float
    最小值：Float.MIN_VALUE=1.4E-45
    最大值：Float.MAX_VALUE=3.4028235E38
    默认值：1.0F

##### double

    基本类型：double 二进制位数：64
   位数组成：符号位=1，指数位=11(其中指数符号位=1)，尾数位=52
    占字节数：8字节
    包装类：java.lang.Double
    最小值：Double.MIN_VALUE=4.9E-324
    最大值：Double.MAX_VALUE=1.7976931348623157E308
    默认值：1.0D

##### char

    基本类型：char 二进制位数：16
    占字节数：2字节
    包装类：java.lang.Character
    最小值：Character.MIN_VALUE=0
    最大值：Character.MAX_VALUE=65535
    默认值：\u0000

##### boolean

    基本数据类型： boolean  二进制位数：1
    占字节数：？未明确定义，
    JVM规范中指出，单独使用时用int类型实现占4个字节，数组中通过byte实现占1个字节
    参考官方：https://docs.oracle.com/javase/tutorial/java/nutsandbolts/datatypes.html
    包装类：java.lang.Boolean
    取值范围：false/true
    默认值：false
    

#### 类型转换

隐式转换：指数据范围小的类型向数据范围大的类型转换，数据类型将自动提升

        byte-->short(char)-->int-->long-->float-->double

显式转换：指数据范围大的类型向数据范围小的类型转换时，需要显式的声明，否则会编译异常

        double-->float-->long-->int-->short(char)-->byte

#### 注意事项
    
    //(错误，整数型变量默认是int型)
    long a=111111111111111111111111
    //(正确，强制转换)
    long a=111111111111111111111111L

    //(错误  浮点数默认类型是double类型)
    float f=6.26
    //(转换正确，强制)
    float f=6.26F
    
    //(错误 浮点数默认类型是double类型)
    float ff=6.26+1;
    //(正确)
    float ff=6.26F+1;
    
    //(错误 浮点数默认类型是double类型)
    float fff=1; fff=fff+1.0; 
    //(正确)
    float fff=1F; fff=fff+1.0; 

    //(错误 整型默认数据类型是int，s+1 隐式转换为了int，int类型赋值给short，需要强制类型转换)
    short s=1; s=s+1;
    //(正确 等价于 s=(int)(s+1)) 
    short s=1； s+=1;
    
    //(正确 int类型隐式会转换为long类型)
    long l=1; l=l+1; 
    
    
#### TIPS

1.使用javap命令反编译.class 可以查看到类型转换的过程

    
    例如： CalculateDemo2,翻译其.class文件；
           
    javap -c CalculateDemo2.class
    
    Compiled from "CalculateDemo2.java"
    public class wang.sunce.teach.base.chapter1.CalculateDemo2 {
      public wang.sunce.teach.base.chapter1.CalculateDemo2();
        Code:
           0: aload_0
           1: invokespecial #1                  // Method java/lang/Object."<init>":()V
           4: return
    
      public static void main(java.lang.String[]);
        Code:
           0: iconst_1
           1: istore_1
           2: iload_1
           3: iconst_1
           4: iadd
           5: i2s
           6: istore_1
           7: return
    }
    
    iconst 表示 int压栈
    istore 表示 存储为本地变量
    iload  表示 从本地变量加载int
    iadd   表示 int 加法
    i2s    表示 int向short的转换

如下地址了解更多JVM指令集：

https://docs.oracle.com/javase/specs/jvms/se7/html/jvms-6.html#
   
2.基本类型其他表示方法
    
    int  i = 1_1;
    short s = 1____1;   
    long l = 1____1L;   
    
    float f = 0.00_1F;
    
    //int i = _1; //wrong
    //int i = 1_; //wrong
    //float f = 1._0F; //wrong
    //float f = 1_.0F; //wrong
    
    定义基本数字类型时，可以使用下划线，但是不可以用于开头与结尾，也不可以用于小数点前后；
    

3.== 与 equals 方法有什么不同
    
    == : 它的作用是判断两个对象的地址是不是相等。即，判断两个对象是不是同一个对象。
        (基本数据类型==比较的是值，引用数据类型==比较的是内存地址)
  
    equals() : 它的作用也是判断两个对象是否相等。    