#### 名称解释

自动装箱：指基本类型向其包装类自动转换的过程。

自动拆箱：指基本类型的包装类向基本类型自动转换的过程。

#### 问题收集

##### 1.如下程序会输出什么结果？
    
        int x = 1;
        Integer a = 1;
        Integer b = Integer.valueOf(1);
        Integer c = new Integer(1);
        System.out.println("x==a? " + (x == a));
        System.out.println("x==b? " + (x == b));
        System.out.println("x==c? " + (x == c));
        System.out.println("a==b? " + (a == b));
        System.out.println("a==c? " + (a == c));
        System.out.println("b==c? " + (b == c));
        System.out.println("a.equals(c)? " + (a.equals(c)));
        System.out.println("b.equals(c)? " + (b.equals(c)));

##### 2.如下程序会又输出什么结果？

        int y = 128;
        Integer e = 128;
        Integer f = Integer.valueOf(128);
        Integer g = new Integer(128);
        System.out.println("y==e? " + (y == e));
        System.out.println("y==f? " + (y == f));
        System.out.println("y==g? " + (y == g));
        System.out.println("e==f? " + (e == f));
        System.out.println("e==g? " + (e == g));
        System.out.println("f==g? " + (f == g));
        System.out.println("e.equals(g)? " + (e.equals(g)));
        System.out.println("f.equals(g)? " + (f.equals(g)));
        
##### 3.什么时候触发自动装箱/拆箱？如何巩固？


#### 问题解答

##### 什么时候触发自动装箱
    
    当基本类型被赋值给包装类时会触发自动装箱(JDK1.5+)，调用Integer.valueOf()方法
    例如：
        Integer a = 1；
    
    我们注意到valueOf方法的注释描述到：始终缓存-128~127的值    
##### 什么时候触发自动拆箱
    
    当包装类参与运算时会触发自动拆箱，调用Integer.intValue()方法，因为参与运算时基本类型做的事情。

##### 如何巩固

    有没有像我一样，理解这些要点时总是可以很快，然而在一定时间周期后，再次看到关于基本类型的题目是还是有可能出错；
    
    其实在遇到基本类型的题目时，首先要问自已一个问题？int跟Integer有什么区别？
    
    * int是基本类型，Integer是包装类型
    
    * byte，short，int，long，包装类型有值的缓存
    
    * 包装类型参与运算时会自动拆箱，基本类型赋值给包装类是会自动装箱
        
    
#### 验证拆箱/装箱

使用 javap -c BoxingDemo.class 反编译代码，验证装箱/拆箱，以下是反编译片段
        
       3: invokestatic  #2                  // Method java/lang/Integer.valueOf:(I)Ljava/lang/Integer;
       6: astore_2
       7: getstatic     #3                  // Field java/lang/System.out:Ljava/io/PrintStream;
      10: new           #4                  // class java/lang/StringBuilder
      13: dup
      14: invokespecial #5                  // Method java/lang/StringBuilder."<init>":()V
      17: ldc           #6                  // String x==a?
      19: invokevirtual #7                  // Method java/lang/StringBuilder.append:(Ljava/lang/String;)Ljava/lang/StringBuilder;
      22: iload_1
      23: aload_2
      24: invokevirtual #8                  // Method java/lang/Integer.intValue:()I
    
    
可以看到 
           
      3: invokestatic  #2   处调用了 Integer.valueOf
     24: invokevirtual #8  处调用了 Integer.intValue
    
     invokevirtual 表示： 调用实例方法
     invokestatic  表示： 调用静态方法
       
如下地址了解更多JVM指令集：

https://docs.oracle.com/javase/specs/jvms/se7/html/jvms-6.html#

    
#### 结果梳理
        
        int x = 1;
        Integer a = 1;//自动装箱
        Integer b = Integer.valueOf(1);
        Integer c = new Integer(1);
        System.out.println("x==a? " + (x == a));//true 自动拆箱
        System.out.println("x==b? " + (x == b));//true 自动拆箱
        System.out.println("x==c? " + (x == c));//true 自动拆箱
        System.out.println("a==b? " + (a == b));//true 永久缓存 -128~127
        System.out.println("a==c? " + (a == c));//false 对象比较引用值
        System.out.println("b==c? " + (b == c));//false 对象比较引用值
        System.out.println("a.equals(c)? " + (a.equals(c)));//true Integer.equals 方法中调用了intValue
        System.out.println("b.equals(c)? " + (b.equals(c)));//true Integer.equals 方法中调用了intValue


        int y = 128;
        Integer e = 128;
        Integer f = Integer.valueOf(128);
        Integer g = new Integer(128);
        System.out.println("y==e? " + (y == e));//true 自动拆箱
        System.out.println("y==f? " + (y == f));//true 自动拆箱
        System.out.println("y==g? " + (y == g));//true 自动拆箱
        System.out.println("e==f? " + (e == f));//false 永久缓存 -128~127
        System.out.println("e==g? " + (e == g));//false 对象比较引用值
        System.out.println("f==g? " + (f == g));//false 对象比较引用值
        System.out.println("e.equals(g)? " + (e.equals(g)));//true Integer.equals 方法中调用了intValue
        System.out.println("f.equals(g)? " + (f.equals(g)));//true Integer.equals 方法中调用了intValue
          
 #### 延伸扩展

        Byte    缓存 -128~127 详见内部类ByteCache
        Short   缓存 -128~127 详见内部类ShortCache
        Integer 缓存 -128~127 详见内部类IntegerCache
        Long    缓存 -128~127 详见内部类LongCache
        Character 缓存 0~127 详见内部类CharacterCache
        Boolean TRUE/FALSE
        Float  无缓存
        Double 无缓存
        
        

    